testbello/__init__.py
testbello-1.1.dist-info/LICENSE.md
testbello-1.1.dist-info/METADATA
testbello-1.1.dist-info/WHEEL
testbello-1.1.dist-info/top_level.txt
testbello-1.1.dist-info/zip-safe
testbello-1.1.dist-info/RECORD
